{
    "title": "Department Course Page",
    "team": [
        {
            "name": "Dharmarathna N.S.",
            "email": "e18077@eng.pdn.ac.lk",
            "eNumber": "E/18/077"
        },
        {
            "name": "Mihiranga G.D.R.",
            "email": "e18224@eng.pdn.ac.lk",
            "eNumber": "E/18/224"
        },
        {
            "name": "Mudalige D.H.",
            "email": "e18227@eng.pdn.ac.lk",
            "eNumber": "E/18/227"
        }
    ],
    "supervisors": [
        {
            "name": "Mr. Nuwan Jaliyagoda",
            "email": "nuwanjaliyagoda@eng.pdn.ac.lk"
        },
        {
            "name": "Mr. Imesh Ekanayake",
            "email": "imeshuek@eng.pdn.ac.lk"
        }
    ],
    "tags": ["Web", "Course Page"]
}
